[
  { "id": 1, "name": "Alice" },
  { "id": 2, "name": "Bob" },
  { "id": 3, "name": "Charlie" },
  { "id": 4, "name": "Diana" },
  { "id": 5, "name": "Evan" },
  { "id": 6, "name": "Fiona" },
  { "id": 7, "name": "George" },
  { "id": 8, "name": "Helen" },
  { "id": 9, "name": "Ian" },
  { "id": 10, "name": "Julia" },
  { "id": 11, "name": "Karan" },
  { "id": 12, "name": "Lina" },
  { "id": 13, "name": "Mohan" },
  { "id": 14, "name": "Nia" },
  { "id": 15, "name": "Omar" },
  { "id": 16, "name": "Preeti" },
  { "id": 17, "name": "Quinn" },
  { "id": 18, "name": "Raj" },
  { "id": 19, "name": "Sam" },
  { "id": 20, "name": "Tara" }
]
